giotto_tda-0.6.2.dist-info/DELVEWHEEL
giotto_tda-0.6.2.dist-info/LICENSE
giotto_tda-0.6.2.dist-info/METADATA
giotto_tda-0.6.2.dist-info/RECORD
giotto_tda-0.6.2.dist-info/top_level.txt
giotto_tda-0.6.2.dist-info/WHEEL
giotto_tda.libs/msvcp140-83c8b2cdd4f51ae13e8f213373318a10.dll
gtda/base.py
gtda/pipeline.py
gtda/_version.py
gtda/__init__.py
gtda/curves/features.py
gtda/curves/preprocessing.py
gtda/curves/_functions.py
gtda/curves/__init__.py
gtda/diagrams/distance.py
gtda/diagrams/features.py
gtda/diagrams/preprocessing.py
gtda/diagrams/representations.py
gtda/diagrams/_features.py
gtda/diagrams/_metrics.py
gtda/diagrams/_utils.py
gtda/diagrams/__init__.py
gtda/externals/__init__.py
gtda/externals/modules/gtda_bottleneck.cp311-win_amd64.pyd
gtda/externals/modules/gtda_cech_complex.cp311-win_amd64.pyd
gtda/externals/modules/gtda_cubical_complex.cp311-win_amd64.pyd
gtda/externals/modules/gtda_periodic_cubical_complex.cp311-win_amd64.pyd
gtda/externals/modules/gtda_persistent_cohomology.cp311-win_amd64.pyd
gtda/externals/modules/gtda_simplex_tree.cp311-win_amd64.pyd
gtda/externals/modules/gtda_sparse_rips_complex.cp311-win_amd64.pyd
gtda/externals/modules/gtda_strong_witness_complex.cp311-win_amd64.pyd
gtda/externals/modules/gtda_wasserstein.cp311-win_amd64.pyd
gtda/externals/modules/gtda_witness_complex.cp311-win_amd64.pyd
gtda/externals/python/cech_complex_interface.py
gtda/externals/python/cubical_complex_interface.py
gtda/externals/python/periodic_cubical_complex_interface.py
gtda/externals/python/rips_complex_interface.py
gtda/externals/python/simplex_tree_interface.py
gtda/externals/python/strong_witness_complex_interface.py
gtda/externals/python/witness_complex_interface.py
gtda/externals/python/__init__.py
gtda/graphs/geodesic_distance.py
gtda/graphs/kneighbors.py
gtda/graphs/transition.py
gtda/graphs/__init__.py
gtda/homology/cubical.py
gtda/homology/simplicial.py
gtda/homology/_utils.py
gtda/homology/__init__.py
gtda/images/filtrations.py
gtda/images/preprocessing.py
gtda/images/_utils.py
gtda/images/__init__.py
gtda/local_homology/simplicial.py
gtda/local_homology/__init__.py
gtda/local_homology/tests/test_simplicial.py
gtda/local_homology/tests/__init__.py
